ilcli/__init__.py
ilcli/actions.py
ilcli/args.py
ilcli/command.py
ilcli-0.3.1.dist-info/LICENSE
ilcli-0.3.1.dist-info/METADATA
ilcli-0.3.1.dist-info/WHEEL
ilcli-0.3.1.dist-info/top_level.txt
ilcli-0.3.1.dist-info/RECORD
